mechanic_pytorch/__about__.py
mechanic_pytorch/__init__.py
mechanic_pytorch/mechanic.py
mechanic_pytorch-0.0.1.dist-info/METADATA
mechanic_pytorch-0.0.1.dist-info/WHEEL
mechanic_pytorch-0.0.1.dist-info/licenses/LICENSE.txt
mechanic_pytorch-0.0.1.dist-info/RECORD
