Metadata-Version: 2.1
Name: mechanic-pytorch
Version: 0.0.1
Summary: black box tuning of optimizers
Project-URL: Documentation, https://github.com/optimizedlearning/mechanic#readme
Project-URL: Issues, https://github.com/optimizedlearning/mechanic/issues
Project-URL: Source, https://github.com/optimizedlearning/mechanic
Author-email: Ashok Cutkosky <ashok@cutkosky.com>
License-Expression: Apache-2.0
License-File: LICENSE.txt
Classifier: Development Status :: 4 - Beta
Classifier: Programming Language :: Python
Classifier: Programming Language :: Python :: 3.7
Classifier: Programming Language :: Python :: 3.8
Classifier: Programming Language :: Python :: 3.9
Classifier: Programming Language :: Python :: 3.10
Classifier: Programming Language :: Python :: 3.11
Classifier: Programming Language :: Python :: Implementation :: CPython
Classifier: Programming Language :: Python :: Implementation :: PyPy
Requires-Python: >=3.7
Requires-Dist: torch>=1.13.1
